README.rst
setup.cfg
setup.py
./__init__.py
./party.py
./transaction.py
./transaction.xml
./tryton.cfg
./tests/conftest.py
./tests/test_payment_gateway.py
./view/gateway_form.xml
./view/payment_profile_form.xml
fio_payment_gateway_stripe.egg-info/PKG-INFO
fio_payment_gateway_stripe.egg-info/SOURCES.txt
fio_payment_gateway_stripe.egg-info/dependency_links.txt
fio_payment_gateway_stripe.egg-info/entry_points.txt
fio_payment_gateway_stripe.egg-info/not-zip-safe
fio_payment_gateway_stripe.egg-info/requires.txt
fio_payment_gateway_stripe.egg-info/top_level.txt